taegis_magic/__init__.py
taegis_magic/_version.py
taegis_magic/cli.py
taegis_magic/magics.py
taegis_magic/commands/__init__.py
taegis_magic/commands/alerts.py
taegis_magic/commands/audits.py
taegis_magic/commands/authentication.py
taegis_magic/commands/cases.py
taegis_magic/commands/clients.py
taegis_magic/commands/configure.py
taegis_magic/commands/events.py
taegis_magic/commands/investigations.py
taegis_magic/commands/notebook.py
taegis_magic/commands/preferences.py
taegis_magic/commands/process_trees.py
taegis_magic/commands/rules.py
taegis_magic/commands/search.py
taegis_magic/commands/sharelinks.py
taegis_magic/commands/subjects.py
taegis_magic/commands/tenant_profiles.py
taegis_magic/commands/tenants.py
taegis_magic/commands/threat.py
taegis_magic/commands/users.py
taegis_magic/commands/utils/__init__.py
taegis_magic/commands/utils/investigations.py
taegis_magic/core/__init__.py
taegis_magic/core/cache.py
taegis_magic/core/callbacks.py
taegis_magic/core/grid.py
taegis_magic/core/log.py
taegis_magic/core/normalizer.py
taegis_magic/core/notebook.py
taegis_magic/core/service.py
taegis_magic/core/utils.py
taegis_magic/core/graphql/__init__.py
taegis_magic/core/graphql/subjects.py
taegis_magic/pandas/__init__.py
taegis_magic/pandas/alerts.py
taegis_magic/pandas/assets.py
taegis_magic/pandas/audits.py
taegis_magic/pandas/context.py
taegis_magic/pandas/events.py
taegis_magic/pandas/investigations.py
taegis_magic/pandas/ioc.py
taegis_magic/pandas/process_trees.py
taegis_magic/pandas/rules.py
taegis_magic/pandas/subjects.py
taegis_magic/pandas/tenants.py
taegis_magic/pandas/utils.py
taegis_magic/templates/__init__.py
taegis_magic/templates/jupyter_extended_markdown_template.jinja
taegis_magic/templates/taegis_results.md.jinja
taegis_magic/templates/taegis_search_results.md.jinja
taegis_magic/templates/template.ipynb
taegis_magic-2026.1.28.dist-info/METADATA
taegis_magic-2026.1.28.dist-info/WHEEL
taegis_magic-2026.1.28.dist-info/entry_points.txt
taegis_magic-2026.1.28.dist-info/licenses/LICENSE
taegis_magic-2026.1.28.dist-info/RECORD
