Metadata-Version: 2.4
Name: taegis-magic
Version: 2026.1.28
Summary: Taegis IPython Magics
Project-URL: Homepage, https://github.com/secureworks/taegis-magic
Project-URL: Bug Reports, https://github.com/secureworks/taegis-magic/issues
Project-URL: Source, https://github.com/secureworks/taegis-magic
Project-URL: Package, https://pypi.org/project/taegis-magic/
Author-email: Micah Pegman <sdks@secureworks.com>
License:                                  Apache License
License-File: LICENSE
Classifier: License :: OSI Approved :: Apache Software License
Classifier: Operating System :: OS Independent
Classifier: Programming Language :: Python :: 3
Classifier: Programming Language :: Python :: 3.9
Classifier: Programming Language :: Python :: 3.10
Classifier: Programming Language :: Python :: 3.11
Classifier: Programming Language :: Python :: 3.12
Classifier: Programming Language :: Python :: 3.13
Requires-Python: >=3.9
Requires-Dist: click
Requires-Dist: compress-pickle>=2.1.0
Requires-Dist: dataclasses-json
Requires-Dist: gql>=4
Requires-Dist: ipylab
Requires-Dist: ipynbname
Requires-Dist: ipython
Requires-Dist: jinja2
Requires-Dist: nbclient
Requires-Dist: nbconvert
Requires-Dist: nbformat
Requires-Dist: notebook
Requires-Dist: pandas<3.0,>=2.1
Requires-Dist: pandas[excel]
Requires-Dist: panel
Requires-Dist: papermill
Requires-Dist: requests
Requires-Dist: tabulator
Requires-Dist: taegis-sdk-python>=1.6.9
Requires-Dist: typer
Provides-Extra: dev
Requires-Dist: black; extra == 'dev'
Requires-Dist: jupyter; extra == 'dev'
Requires-Dist: pylint; extra == 'dev'
Provides-Extra: grid
Requires-Dist: ipydatagrid; extra == 'grid'
